nonebot_plugin_function/__init__.py
nonebot_plugin_function-0.1.8.4.dist-info/LICENSE
nonebot_plugin_function-0.1.8.4.dist-info/METADATA
nonebot_plugin_function-0.1.8.4.dist-info/WHEEL
nonebot_plugin_function-0.1.8.4.dist-info/top_level.txt
nonebot_plugin_function-0.1.8.4.dist-info/RECORD
