Metadata-Version: 2.1
Name: nonebot-plugin-function
Version: 0.1.8.4
Summary: 奇怪的东西
Requires-Python: <4.0,>=3.9
License-File: LICENSE
Requires-Dist: nonebot-adapter-onebot>=2.4.4
Requires-Dist: nonebot-plugin-waiter>=0.7.1
Requires-Dist: nonebot-plugin-alconna>=0.50.2
Requires-Dist: httpx>=0.27.0
